knocker/__init__.py
knocker/consumers.py
knocker/mixins.py
knocker/models.py
knocker/routing.py
knocker/signals.py
knocker/static/js/knocker.js
django_knocker-0.5.1.dist-info/LICENSE
django_knocker-0.5.1.dist-info/METADATA
django_knocker-0.5.1.dist-info/WHEEL
django_knocker-0.5.1.dist-info/top_level.txt
django_knocker-0.5.1.dist-info/RECORD
