Metadata-Version: 2.1
Name: django-knocker
Version: 0.5.1
Summary: Channels-based desktop notification system
Home-page: https://github.com/nephila/django-knocker
Author: Iacopo Spalletti
Author-email: i.spalletti@nephila.it
License: BSD
Project-URL: Documentation, https://django-knocker.readthedocs.io/
Classifier: License :: OSI Approved :: BSD License
Classifier: Development Status :: 5 - Production/Stable
Classifier: Framework :: Django
Classifier: Framework :: Django :: 3.2
Classifier: Framework :: Django :: 4.0
Classifier: Framework :: Django :: 4.1
Classifier: Framework :: Django :: 4.2
Classifier: Programming Language :: Python
Classifier: Programming Language :: Python :: 3
Classifier: Programming Language :: Python :: 3.9
Classifier: Programming Language :: Python :: 3.10
Classifier: Programming Language :: Python :: 3.11
Requires-Python: >=3.7
License-File: LICENSE
Requires-Dist: channels (<5,>=4)
Requires-Dist: django-meta (>=1.4)
